decision_title_vs_inre/__init__.py
decision_title_vs_inre/__main__.py
decision_title_vs_inre/checked_latin.py
decision_title_vs_inre/dated_exp.py
decision_title_vs_inre/extras/__init__.py
decision_title_vs_inre/extras/brackets.py
decision_title_vs_inre/extras/party_replace.py
decision_title_vs_inre/extras/plaintiff_cleaning_regexes.py
decision_title_vs_inre/indicators/__init__.py
decision_title_vs_inre/indicators/capped.py
decision_title_vs_inre/indicators/latined.py
decision_title_vs_inre/indicators/liner.py
decision_title_vs_inre/indicators/paged.py
decision_title_vs_inre/inre.py
decision_title_vs_inre/vs.py
decision_title_vs_inre/vs_em.py
decision_title_vs_inre-0.0.1.dist-info/WHEEL
decision_title_vs_inre-0.0.1.dist-info/METADATA
decision_title_vs_inre-0.0.1.dist-info/RECORD
